{
    "schain_info": {
        "schain_struct": {
            "name": "3IUYGV0G",
            "owner": "0xE11Bb4DDc05D2C32D3AE8c93F61b76F84f10B1a7",
            "indexInOwnerList": 0,
            "partOfNode": 0,
            "lifetime": 31622400,
            "startDate": 1557935965,
            "deposit": 1000000000000000000,
            "index": 2
        },
        "schain_nodes": [
            {
                "nodeID": 1,
                "nodeName": "dyf2h7MI9opLh",
                "basePort": 8022,
                "httpRpcPort": 8024,
                "httpsRpcPort": 8029,
                "wsRpcPort": 8025,
                "wssRpcPort": 8030,
                "publicKey": "7f765c8f2f567117b751fddaec1644fa8cc9a01790c945c8889d52cabb8213bdb506bf30592b08d5f9dbf7aa018b95918f04516e0a4c5344c8ae1bb5674978b4",
                "owner": "0x934e00268ccae1c1dae04e4233a1bc51d959d2f1",
                "schainIndex": 0,
                "ip": "159.65.71.82",
                "publicIP": "159.65.71.82"
            },
            {
                "nodeID": 0,
                "nodeName": "z6vCFeTzU60zh",
                "basePort": 8022,
                "httpRpcPort": 8024,
                "httpsRpcPort": 8029,
                "wsRpcPort": 8025,
                "wssRpcPort": 8030,
                "publicKey": "ce0319ebd008661bc4e6b99462874a03b87206d32dc6f29a9d54d3dc36804223cea52d5b886e47858d96a184503656ef28bd2cfb79c92bf27458de4d7513575e",
                "owner": "0x730eff2cf85f46c0f62181608230608dfed12f9f",
                "schainIndex": 1,
                "ip": "159.65.106.215",
                "publicIP": "159.65.106.215"
            }
        ]
    },
    "wallet": {
        "address": "0xE11Bb4DDc05D2C32D3AE8c93F61b76F84f10B1a7",
        "private_key": "0x8d39bea8a30fd5a3e660bde9d69b48e024cf5cb38a44083c3bdbc6038a284798"
    }
}